gitgossip/__init__.py
gitgossip/cli.py
gitgossip/commands/__init__.py
gitgossip/commands/init.py
gitgossip/commands/list_authors.py
gitgossip/commands/summarize.py
gitgossip/commands/summarize_mr.py
gitgossip/config/__init__.py
gitgossip/config/config_service.py
gitgossip/core/__init__.py
gitgossip/core/constants.py
gitgossip/core/factories/llm_analyzer_factory.py
gitgossip/core/interfaces/commit_parser.py
gitgossip/core/interfaces/llm_analyzer.py
gitgossip/core/interfaces/repo_discover_service.py
gitgossip/core/interfaces/repo_provider.py
gitgossip/core/interfaces/summarizer_service.py
gitgossip/core/llm/llm_analyzer.py
gitgossip/core/llm/mock_llm_analyzer.py
gitgossip/core/llm/prompt_builder.py
gitgossip/core/llm/prompts/chunk.txt
gitgossip/core/llm/prompts/final.txt
gitgossip/core/llm/prompts/synthesis.txt
gitgossip/core/models/__init__.py
gitgossip/core/models/commit.py
gitgossip/core/parsers/__init__.py
gitgossip/core/parsers/commit_parser.py
gitgossip/core/providers/git_repo_provider.py
gitgossip/core/services/repo_discovery_service.py
gitgossip/core/services/summarizer_service.py
gitgossip/utils/__init__.py
gitgossip/utils/parse.py
gitgossip-0.1.1.dist-info/METADATA
gitgossip-0.1.1.dist-info/WHEEL
gitgossip-0.1.1.dist-info/entry_points.txt
gitgossip-0.1.1.dist-info/licenses/LICENSE
gitgossip-0.1.1.dist-info/RECORD
