Metadata-Version: 2.4
Name: gitgossip
Version: 0.1.1
Summary: AI that spills the tea on your commits — human-readable Git summaries.
Author: Osman Goni Nahid
License: MIT
License-File: LICENSE
Requires-Python: <3.13,>=3.9
Requires-Dist: gitpython>=3.1.45
Requires-Dist: openai>=2.3.0
Requires-Dist: psutil>=7.1.0
Requires-Dist: pydantic==2.8.0
Requires-Dist: rich>=14.1.0
Requires-Dist: ruamel-yaml>=0.18.15
Requires-Dist: typer>=0.9.0
Provides-Extra: dev
Requires-Dist: black; extra == 'dev'
Requires-Dist: isort; extra == 'dev'
Requires-Dist: mypy>=1.18.2; extra == 'dev'
Requires-Dist: pre-commit>=4.3.0; extra == 'dev'
Requires-Dist: pylint>=3.3.9; extra == 'dev'
Requires-Dist: pytest; extra == 'dev'
Requires-Dist: ruff>=0.14.0; extra == 'dev'
